Workbook

Sheet README
B1: Cendoor financial model (MAD)
B3: What this is
B4: A simple monthly model of a subscription business: paying sellers x price, minus the direct cost of serving each seller, minus fixed costs. It is built from founder/numbers.json and the CFO tool output, so its results should match them (see the check on the Summary sheet).
B6: How to use it
B7: Blue cells on a yellow fill are the inputs you can change (Assumptions and Ramp). Black cells are formulas. Change an input and every sheet updates.
B8: Sheets: Assumptions (prices, costs), Model (36 months), Summary (year 1 to 3, break-even, cash needed, check against the CFO tool), Sensitivity (break-even for different prices and founder pay), Market (top-down market sizing).
B10: Read this before relying on it
B11: 1. Almost every cost is an ESTIMATE with no quote. Sources and status are in founder/cfo-sources.md. The WhatsApp provider fee is a vendor-published figure, unverified.
B12: 2. The ramp of paying sellers (months 1 to 12) is an assumption from the CFO model. It is NOT a forecast and no real seller has paid yet. Months 13 to 36 simply add a fixed number of sellers a month (an assumption you can change).
B13: 3. The founder is paid 0 by default. Put a salary in Assumptions to see the honest picture: break-even rises sharply.
B14: 4. No churn is modelled: the ramp is net paying sellers. Add churn by lowering the ramp.
B15: 5. The market figures are assumptions, not statistics: no official count of social-media sellers exists. See docs/investor/market-sizing.md.
... B19: Blue text = input. Black = formula. Yellow fill = a key assumption to review. Amounts are in MAD unless a header says USD.

Sheet Assumptions
A1: Assumptions (MAD)
A2: Item | B2: Value | C2: Source / status
A3: Price per paying seller (MAD / month) | B3: 149 | C3: Solo plan. Founding price is 99; test both. Source: founder plan.
A4: Variable cost per paying seller (MAD / month) | B4: 22.8 | C4: ESTIMATE: WhatsApp messages 12, AI usage 5, payment fees about 3.7, storage 2 = 22.7; the CFO tool rounds to 0.76 per day x 30 = 22.8. founder/cfo-sources.md
A6: Fixed costs per month
A7: Hosting with headroom | B7: 150 | C7: Render Starter about 95 MAD + disk; rounded up. Estimate.
A8: Domain, email, tools | B8: 100 | C8: Estimate.
A9: Accountant and data-protection (CNDP) reserve | B9: 400 | C9: Estimate; no quote.
A10: WhatsApp provider platform fee | B10: 290 | C10: One provider lists about 290 MAD/month for its entry plan (vendor blog, unverified).
A11: Marketing: ads and creators | B11: 2000 | C11: Estimate; the founder has not set a budget.
A12: Founder pay (MAD / month) | B12: 0 | C12: NOT included in the CFO model. Enter a salary to see the real break-even.
A13: Total fixed costs per month | B13: =SUM(B7:B12)
A15: One-off startup spend
A16: Company registration and first accounting | B16: 6000 | C16: Estimate; no quote.
A17: Legal advice incl. CNDP (Law 09-08) | B17: 5000 | C17: Estimate; no quote.
A18: Brand, domain, setup | B18: 1000 | C18: Estimate; no quote.
A19: Launch marketing and pilot incentives | B19: 5000 | C19: Estimate; no quote.
A20: WhatsApp provider onboarding | B20: 2000 | C20: Estimate; no quote.
A21: Total startup spend | B21: =SUM(B16:B20)
A23: Net new paying sellers per month after month 12 | B23: 6 | C23: ASSUMPTION: months 1 to 12 come from the CFO ramp (Model sheet); after that this many are added each month.
A24: MAD per USD (for USD figures) | B24: 10 | C24: Rough assumption, not a quote.
A25: Contribution per paying seller (MAD / month) | B25: =B3-B4
A26: Contribution margin | B26: =IF(B3=0,0,B25/B3)

Sheet Model
A1: Monthly model, 36 months (MAD)
A2: Paying sellers for months 1 to 12 are inputs (the CFO ramp); months 13 to 36 add the net new sellers set in Assumptions.
A3: Month | B3: Paying sellers (end of month) | C3: Revenue | D3: Variable costs | E3: Contribution | F3: Fixed costs (incl. founder pay) | G3: Operating profit | H3: Cumulative cash (after startup spend) | I3: Profit positive? (1 = yes)
A4: 1 | B4: 0 | C4: =B4*Assumptions!$B$3 | D4: =B4*Assumptions!$B$4 | E4: =C4-D4 | F4: =Assumptions!$B$13 | G4: =E4-F4 | H4: =-Assumptions!$B$21+G4 | I4: =IF(G4>0,1,0)
A5: 2 | B5: 3 | C5: =B5*Assumptions!$B$3 | D5: =B5*Assumptions!$B$4 | E5: =C5-D5 | F5: =Assumptions!$B$13 | G5: =E5-F5 | H5: =H4+G5 | I5: =IF(G5>0,1,0)
A6: 3 | B6: 6 | C6: =B6*Assumptions!$B$3 | D6: =B6*Assumptions!$B$4 | E6: =C6-D6 | F6: =Assumptions!$B$13 | G6: =E6-F6 | H6: =H5+G6 | I6: =IF(G6>0,1,0)
A7: 4 | B7: 10 | C7: =B7*Assumptions!$B$3 | D7: =B7*Assumptions!$B$4 | E7: =C7-D7 | F7: =Assumptions!$B$13 | G7: =E7-F7 | H7: =H6+G7 | I7: =IF(G7>0,1,0)
A8: 5 | B8: 15 | C8: =B8*Assumptions!$B$3 | D8: =B8*Assumptions!$B$4 | E8: =C8-D8 | F8: =Assumptions!$B$13 | G8: =E8-F8 | H8: =H7+G8 | I8: =IF(G8>0,1,0)
A9: 6 | B9: 20 | C9: =B9*Assumptions!$B$3 | D9: =B9*Assumptions!$B$4 | E9: =C9-D9 | F9: =Assumptions!$B$13 | G9: =E9-F9 | H9: =H8+G9 | I9: =IF(G9>0,1,0)
A10: 7 | B10: 26 | C10: =B10*Assumptions!$B$3 | D10: =B10*Assumptions!$B$4 | E10: =C10-D10 | F10: =Assumptions!$B$13 | G10: =E10-F10 | H10: =H9+G10 | I10: =IF(G10>0,1,0)
A11: 8 | B11: 32 | C11: =B11*Assumptions!$B$3 | D11: =B11*Assumptions!$B$4 | E11: =C11-D11 | F11: =Assumptions!$B$13 | G11: =E11-F11 | H11: =H10+G11 | I11: =IF(G11>0,1,0)
A12: 9 | B12: 38 | C12: =B12*Assumptions!$B$3 | D12: =B12*Assumptions!$B$4 | E12: =C12-D12 | F12: =Assumptions!$B$13 | G12: =E12-F12 | H12: =H11+G12 | I12: =IF(G12>0,1,0)
A13: 10 | B13: 45 | C13: =B13*Assumptions!$B$3 | D13: =B13*Assumptions!$B$4 | E13: =C13-D13 | F13: =Assumptions!$B$13 | G13: =E13-F13 | H13: =H12+G13 | I13: =IF(G13>0,1,0)
A14: 11 | B14: 52 | C14: =B14*Assumptions!$B$3 | D14: =B14*Assumptions!$B$4 | E14: =C14-D14 | F14: =Assumptions!$B$13 | G14: =E14-F14 | H14: =H13+G14 | I14: =IF(G14>0,1,0)
A15: 12 | B15: 60 | C15: =B15*Assumptions!$B$3 | D15: =B15*Assumptions!$B$4 | E15: =C15-D15 | F15: =Assumptions!$B$13 | G15: =E15-F15 | H15: =H14+G15 | I15: =IF(G15>0,1,0)
A16: 13 | B16: =B15+Assumptions!$B$23 | C16: =B16*Assumptions!$B$3 | D16: =B16*Assumptions!$B$4 | E16: =C16-D16 | F16: =Assumptions!$B$13 | G16: =E16-F16 | H16: =H15+G16 | I16: =IF(G16>0,1,0)
A17: 14 | B17: =B16+Assumptions!$B$23 | C17: =B17*Assumptions!$B$3 | D17: =B17*Assumptions!$B$4 | E17: =C17-D17 | F17: =Assumptions!$B$13 | G17: =E17-F17 | H17: =H16+G17 | I17: =IF(G17>0,1,0)
A18: 15 | B18: =B17+Assumptions!$B$23 | C18: =B18*Assumptions!$B$3 | D18: =B18*Assumptions!$B$4 | E18: =C18-D18 | F18: =Assumptions!$B$13 | G18: =E18-F18 | H18: =H17+G18 | I18: =IF(G18>0,1,0)
A19: 16 | B19: =B18+Assumptions!$B$23 | C19: =B19*Assumptions!$B$3 | D19: =B19*Assumptions!$B$4 | E19: =C19-D19 | F19: =Assumptions!$B$13 | G19: =E19-F19 | H19: =H18+G19 | I19: =IF(G19>0,1,0)
A20: 17 | B20: =B19+Assumptions!$B$23 | C20: =B20*Assumptions!$B$3 | D20: =B20*Assumptions!$B$4 | E20: =C20-D20 | F20: =Assumptions!$B$13 | G20: =E20-F20 | H20: =H19+G20 | I20: =IF(G20>0,1,0)
A21: 18 | B21: =B20+Assumptions!$B$23 | C21: =B21*Assumptions!$B$3 | D21: =B21*Assumptions!$B$4 | E21: =C21-D21 | F21: =Assumptions!$B$13 | G21: =E21-F21 | H21: =H20+G21 | I21: =IF(G21>0,1,0)
A22: 19 | B22: =B21+Assumptions!$B$23 | C22: =B22*Assumptions!$B$3 | D22: =B22*Assumptions!$B$4 | E22: =C22-D22 | F22: =Assumptions!$B$13 | G22: =E22-F22 | H22: =H21+G22 | I22: =IF(G22>0,1,0)
A23: 20 | B23: =B22+Assumptions!$B$23 | C23: =B23*Assumptions!$B$3 | D23: =B23*Assumptions!$B$4 | E23: =C23-D23 | F23: =Assumptions!$B$13 | G23: =E23-F23 | H23: =H22+G23 | I23: =IF(G23>0,1,0)
A24: 21 | B24: =B23+Assumptions!$B$23 | C24: =B24*Assumptions!$B$3 | D24: =B24*Assumptions!$B$4 | E24: =C24-D24 | F24: =Assumptions!$B$13 | G24: =E24-F24 | H24: =H23+G24 | I24: =IF(G24>0,1,0)
A25: 22 | B25: =B24+Assumptions!$B$23 | C25: =B25*Assumptions!$B$3 | D25: =B25*Assumptions!$B$4 | E25: =C25-D25 | F25: =Assumptions!$B$13 | G25: =E25-F25 | H25: =H24+G25 | I25: =IF(G25>0,1,0)
A26: 23 | B26: =B25+Assumptions!$B$23 | C26: =B26*Assumptions!$B$3 | D26: =B26*Assumptions!$B$4 | E26: =C26-D26 | F26: =Assumptions!$B$13 | G26: =E26-F26 | H26: =H25+G26 | I26: =IF(G26>0,1,0)
A27: 24 | B27: =B26+Assumptions!$B$23 | C27: =B27*Assumptions!$B$3 | D27: =B27*Assumptions!$B$4 | E27: =C27-D27 | F27: =Assumptions!$B$13 | G27: =E27-F27 | H27: =H26+G27 | I27: =IF(G27>0,1,0)
... A39: 36 | B39: =B38+Assumptions!$B$23 | C39: =B39*Assumptions!$B$3 | D39: =B39*Assumptions!$B$4 | E39: =C39-D39 | F39: =Assumptions!$B$13 | G39: =E39-F39 | H39: =H38+G39 | I39: =IF(G39>0,1,0)

Sheet Summary
A1: Summary (MAD)
B3: Year 1 | C3: Year 2 | D3: Year 3
A4: Paying sellers at end of year | B4: =Model!B15 | C4: =Model!B27 | D4: =Model!B39
A5: Revenue | B5: =SUM(Model!C4:C15) | C5: =SUM(Model!C16:C27) | D5: =SUM(Model!C28:C39)
A6: Variable costs | B6: =SUM(Model!D4:D15) | C6: =SUM(Model!D16:D27) | D6: =SUM(Model!D28:D39)
A7: Contribution | B7: =SUM(Model!E4:E15) | C7: =SUM(Model!E16:E27) | D7: =SUM(Model!E28:E39)
A8: Fixed costs (incl. founder pay) | B8: =SUM(Model!F4:F15) | C8: =SUM(Model!F16:F27) | D8: =SUM(Model!F28:F39)
A9: Operating profit | B9: =SUM(Model!G4:G15) | C9: =SUM(Model!G16:G27) | D9: =SUM(Model!G28:G39)
A10: Operating profit after startup spend (year 1) | B10: =B9-Assumptions!B21
A12: Break-even and cash
A13: Break-even: paying sellers needed | B13: =IF(Assumptions!B25<=0,"n/a",ROUNDUP(Assumptions!B13/Assumptions!B25,0))
A14: Month the monthly operating profit first turns positive | B14: =IFERROR(INDEX(Model!A4:A39,MATCH(1,Model!I4:I39,0)),"not within 36 months")
A15: Cash needed before it pays for itself (lowest cumulative cash) | B15: =MAX(0,-MIN(Model!H4:H39))
A16: Cash needed in USD | B16: =B15/Assumptions!B24
A17: Year 1 revenue in USD | B17: =B5/Assumptions!B24
A19: Check against the CFO tool (founder/cfo.md)
A20: CFO tool: year 1 operating profit (MAD, price 149.1, no founder pay) | B20: 3494 | E20: Copied from founder/cfo.md. The tool uses 4.97 per day x 30 = 149.1 and 0.76 x 30 = 22.8.
A21: This model: year 1 operating profit (set founder pay to 0 and price to 149.1 to match exactly) | B21: =B9
A22: Difference | B22: =B21-B20 | C22: =IF(B20=0,0,B22/B20) | E22: Within about 1% when price is 149 (the tool rounds the price to 149.1). A larger gap means an input differs from numbers.json.

Sheet Sensitivity
A1: Break-even paying sellers: price vs founder pay
A2: Each cell = (fixed costs excluding founder pay + founder pay) / (price - variable cost), rounded up. Prices and pay levels are editable inputs.
A4: Price (MAD / month) \ Founder pay (MAD / month) | B4: 0 | C4: 3000 | D4: 6000 | E4: 10000
A5: 99 | B5: =IF($A5-Assumptions!$B$4<=0,"n/a",ROUNDUP((Assumptions!$B$13-Assumptions!$B$12+B$4)/($A5-Assumptions!$B$4),0)) | C5: =IF($A5-Assumptions!$B$4<=0,"n/a",ROUNDUP((Assumptions!$B$13-Assumptions!$B$12+C$4)/($A5-Assumptions!$B$4),0)) | D5: =IF($A5-Assumptions!$B$4<=0,"n/a",ROUNDUP((Assumptions!$B$13-Assumptions!$B$12+D$4)/($A5-Assumptions!$B$4),0)) | E5: =IF($A5-Assumptions!$B$4<=0,"n/a",ROUNDUP((Assumptions!$B$13-Assumptions!$B$12+E$4)/($A5-Assumptions!$B$4),0))
A6: 149 | B6: =IF($A6-Assumptions!$B$4<=0,"n/a",ROUNDUP((Assumptions!$B$13-Assumptions!$B$12+B$4)/($A6-Assumptions!$B$4),0)) | C6: =IF($A6-Assumptions!$B$4<=0,"n/a",ROUNDUP((Assumptions!$B$13-Assumptions!$B$12+C$4)/($A6-Assumptions!$B$4),0)) | D6: =IF($A6-Assumptions!$B$4<=0,"n/a",ROUNDUP((Assumptions!$B$13-Assumptions!$B$12+D$4)/($A6-Assumptions!$B$4),0)) | E6: =IF($A6-Assumptions!$B$4<=0,"n/a",ROUNDUP((Assumptions!$B$13-Assumptions!$B$12+E$4)/($A6-Assumptions!$B$4),0))
A7: 199 | B7: =IF($A7-Assumptions!$B$4<=0,"n/a",ROUNDUP((Assumptions!$B$13-Assumptions!$B$12+B$4)/($A7-Assumptions!$B$4),0)) | C7: =IF($A7-Assumptions!$B$4<=0,"n/a",ROUNDUP((Assumptions!$B$13-Assumptions!$B$12+C$4)/($A7-Assumptions!$B$4),0)) | D7: =IF($A7-Assumptions!$B$4<=0,"n/a",ROUNDUP((Assumptions!$B$13-Assumptions!$B$12+D$4)/($A7-Assumptions!$B$4),0)) | E7: =IF($A7-Assumptions!$B$4<=0,"n/a",ROUNDUP((Assumptions!$B$13-Assumptions!$B$12+E$4)/($A7-Assumptions!$B$4),0))
A8: 299 | B8: =IF($A8-Assumptions!$B$4<=0,"n/a",ROUNDUP((Assumptions!$B$13-Assumptions!$B$12+B$4)/($A8-Assumptions!$B$4),0)) | C8: =IF($A8-Assumptions!$B$4<=0,"n/a",ROUNDUP((Assumptions!$B$13-Assumptions!$B$12+C$4)/($A8-Assumptions!$B$4),0)) | D8: =IF($A8-Assumptions!$B$4<=0,"n/a",ROUNDUP((Assumptions!$B$13-Assumptions!$B$12+D$4)/($A8-Assumptions!$B$4),0)) | E8: =IF($A8-Assumptions!$B$4<=0,"n/a",ROUNDUP((Assumptions!$B$13-Assumptions!$B$12+E$4)/($A8-Assumptions!$B$4),0))
A10: Reading it: at 99 MAD with no founder pay you need about 39 paying sellers; at 149 MAD about 24; with a 6,000 MAD salary at 149 MAD about 71.

Sheet Market
A1: Market sizing: assumptions, not statistics
A2: No official count of social-media sellers in Morocco exists. Replace the blue cells with survey data. Sources for the anchors: docs/investor/market-sizing.md.
B4: Low | C4: Base | D4: High | E4: Basis
A5: TAM: sellers who sell via social media or messaging | B5: 50000 | C5: 100000 | D5: 150000 | E5: ASSUMPTION. Anchor: 463,383 auto-entrepreneurs at end of 2025 (a minority sell online) plus unregistered sellers.
A6: Share who are regular sellers, take COD and would pay (SAM share) | B6: 0.3 | C6: 0.3 | D6: 0.3 | E6: ASSUMPTION. The simulated panel (an upper bound) said 25% would try the offer.
A7: SAM: serviceable sellers | B7: =B5*B6 | C7: =C5*C6 | D7: =D5*D6
A8: Share Cendoor wins in 3 years (SOM share) | B8: 0.03 | C8: 0.04 | D8: 0.05 | E8: ASSUMPTION.
A9: SOM: paying sellers in year 3 | B9: =B7*B8 | C9: =C7*C8 | D9: =D7*D8
A10: Annual revenue at the model price (MAD) | B10: =B9*Assumptions!$B$3*12 | C10: =C9*Assumptions!$B$3*12 | D10: =D9*Assumptions!$B$3*12
A11: Annual revenue (USD) | B11: =B10/Assumptions!$B$24 | C11: =C10/Assumptions!$B$24 | D11: =D10/Assumptions!$B$24
A12: SAM as annual revenue (MAD) | B12: =B7*Assumptions!$B$3*12 | C12: =C7*Assumptions!$B$3*12 | D12: =D7*Assumptions!$B$3*12
A14: Reading it: even the high case is a few hundred thousand USD a year in Morocco alone. Investor-scale needs more revenue per seller, expansion, or a much larger seller base, all unproven.
